XpGraph-0.0.1.data/scripts/XpG.py
xpg/__init__.py
xpg/axp.py
xpg/cxp.py
xpg/xpg.py
XpGraph-0.0.1.dist-info/METADATA
XpGraph-0.0.1.dist-info/WHEEL
XpGraph-0.0.1.dist-info/top_level.txt
XpGraph-0.0.1.dist-info/RECORD
