Metadata-Version: 2.1
Name: XpGraph
Version: 0.0.1
Summary: Explaining Graph-based Classifiers
Home-page: https://github.com/yizza91/xpg
Author: Xuanxiang Huang, Yacine Izza, Alexey Ignatiev, Joao Marques-Silva
Author-email: yacine.izza@gmail.com
License: GPL
Platform: UNKNOWN
Requires-Dist: networkx
Requires-Dist: numpy
Requires-Dist: python-sat
